{
    "Ar36": {
        "error": 0.0006190567418912498, 
        "filter_outliers_dict": {
            "filter_outliers": true, 
            "iterations": 1, 
            "std_devs": 10
        }, 
        "fit": "Parabolic", 
        "fn": 120, 
        "include_baseline_error": false, 
        "n": 120, 
        "value": 0.008399585919896348
    }, 
    "Ar37": {
        "error": 0.009309202944795458, 
        "filter_outliers_dict": {
            "filter_outliers": true, 
            "iterations": 1, 
            "std_devs": 2
        }, 
        "fit": "Linear", 
        "fn": 114, 
        "include_baseline_error": false, 
        "n": 120, 
        "value": 0.05572697001296357
    }, 
    "Ar38": {
        "error": 0.0043907453204484, 
        "filter_outliers_dict": {
            "filter_outliers": true, 
            "iterations": 1, 
            "std_devs": 2
        }, 
        "fit": "Linear", 
        "fn": 115, 
        "include_baseline_error": false, 
        "n": 120, 
        "value": -0.005298667532343714
    }, 
    "Ar39": {
        "error": 0.02519375371386148, 
        "filter_outliers_dict": {
            "filter_outliers": true, 
            "iterations": 1, 
            "std_devs": 2
        }, 
        "fit": "Parabolic", 
        "fn": 115, 
        "include_baseline_error": false, 
        "n": 120, 
        "value": 1.0882741148938397
    }, 
    "Ar40": {
        "error": 0.019659441500691446, 
        "filter_outliers_dict": {
            "filter_outliers": true, 
            "iterations": 1, 
            "std_devs": 2
        }, 
        "fit": "Parabolic", 
        "fn": 117, 
        "include_baseline_error": false, 
        "n": 120, 
        "value": 2.666539302639657
    }, 
    "Ar41": {
        "error": 0.003308217830086417, 
        "filter_outliers_dict": {
            "filter_outliers": true, 
            "iterations": 1, 
            "std_devs": 2
        }, 
        "fit": "Average", 
        "fn": 116, 
        "include_baseline_error": false, 
        "n": 120, 
        "value": -0.07007688650427836
    }, 
    "reviewed": true
}