{
    "Ar36": {
        "error": 0.0002287234835214009, 
        "filter_outliers_dict": {
            "filter_outliers": true, 
            "iterations": 1, 
            "std_devs": 2
        }, 
        "fit": "Parabolic", 
        "value": 0.011239894129325332
    }, 
    "Ar37": {
        "error": 0.004833332695732136, 
        "filter_outliers_dict": {
            "filter_outliers": true, 
            "iterations": 1, 
            "std_devs": 2
        }, 
        "fit": "linear", 
        "value": 0.05018713070506798
    }, 
    "Ar38": {
        "error": 0.0024286589906503436, 
        "filter_outliers_dict": {
            "filter_outliers": true, 
            "iterations": 1, 
            "std_devs": 2
        }, 
        "fit": "linear", 
        "value": 0.009213169937134875
    }, 
    "Ar39": {
        "error": 0.009430167802095178, 
        "filter_outliers_dict": {
            "filter_outliers": true, 
            "iterations": 1, 
            "std_devs": 2
        }, 
        "fit": "Parabolic", 
        "value": 2.118297883172499
    }, 
    "Ar40": {
        "error": 0.010530684933525892, 
        "filter_outliers_dict": {
            "filter_outliers": true, 
            "iterations": 1, 
            "std_devs": 2
        }, 
        "fit": "Parabolic", 
        "value": 29.01332382825563
    }, 
    "Ar41": {
        "error": 0.0035265838460953503, 
        "filter_outliers_dict": {
            "filter_outliers": true, 
            "iterations": 1, 
            "std_devs": 2
        }, 
        "fit": "linear", 
        "value": -0.07708121645278818
    }
}