{
    "Ar36": {
        "error": 0.00023114833653473286, 
        "filter_outliers_dict": {
            "filter_outliers": true, 
            "iterations": 1, 
            "std_devs": 10
        }, 
        "fit": "Parabolic", 
        "fn": 399, 
        "include_baseline_error": false, 
        "n": 400, 
        "value": 0.009554029132203514
    }, 
    "Ar37": {
        "error": 0.004992865176815768, 
        "filter_outliers_dict": {
            "filter_outliers": true, 
            "iterations": 1, 
            "std_devs": 2
        }, 
        "fit": "Linear", 
        "fn": 387, 
        "include_baseline_error": false, 
        "n": 400, 
        "value": 0.09652607333942018
    }, 
    "Ar38": {
        "error": 0.002476081073801191, 
        "filter_outliers_dict": {
            "filter_outliers": true, 
            "iterations": 1, 
            "std_devs": 2
        }, 
        "fit": "Linear", 
        "fn": 384, 
        "include_baseline_error": false, 
        "n": 400, 
        "value": 0.15167473164131517
    }, 
    "Ar39": {
        "error": 0.01034271347342113, 
        "filter_outliers_dict": {
            "filter_outliers": true, 
            "iterations": 1, 
            "std_devs": 2
        }, 
        "fit": "Parabolic", 
        "fn": 384, 
        "include_baseline_error": false, 
        "n": 400, 
        "value": 13.683747660023052
    }, 
    "Ar40": {
        "error": 0.009434469103887705, 
        "filter_outliers_dict": {
            "filter_outliers": true, 
            "iterations": 1, 
            "std_devs": 2
        }, 
        "fit": "Parabolic", 
        "fn": 386, 
        "include_baseline_error": false, 
        "n": 400, 
        "value": 20.41858634792697
    }, 
    "Ar41": {
        "error": 0.0017129714888567953, 
        "filter_outliers_dict": {
            "filter_outliers": true, 
            "iterations": 1, 
            "std_devs": 2
        }, 
        "fit": "Average", 
        "fn": 390, 
        "include_baseline_error": false, 
        "n": 400, 
        "value": -0.07944479344258956
    }, 
    "reviewed": true
}