{
    "Ar36": {
        "error": 0.0003258425869458494, 
        "filter_outliers_dict": {
            "filter_outliers": true, 
            "iterations": 1, 
            "std_devs": 2
        }, 
        "fit": "Linear", 
        "value": 0.013241553786672158
    }, 
    "Ar37": {
        "error": 0.009273334632937608, 
        "filter_outliers_dict": {
            "filter_outliers": true, 
            "iterations": 1, 
            "std_devs": 2
        }, 
        "fit": "linear", 
        "value": 0.06146288491185241
    }, 
    "Ar38": {
        "error": 0.004468035190165389, 
        "filter_outliers_dict": {
            "filter_outliers": true, 
            "iterations": 1, 
            "std_devs": 2
        }, 
        "fit": "linear", 
        "value": 5.2806355329711966e-05
    }, 
    "Ar39": {
        "error": 0.013040643405495713, 
        "filter_outliers_dict": {
            "filter_outliers": true, 
            "iterations": 1, 
            "std_devs": 2
        }, 
        "fit": "Linear", 
        "value": 1.2769972767006235
    }, 
    "Ar40": {
        "error": 0.009318882488182537, 
        "filter_outliers_dict": {
            "filter_outliers": true, 
            "iterations": 1, 
            "std_devs": 2
        }, 
        "fit": "Linear", 
        "value": 4.451067657860896
    }, 
    "Ar41": {
        "error": 0.003688490150064386, 
        "filter_outliers_dict": {
            "filter_outliers": true, 
            "iterations": 1, 
            "std_devs": 2
        }, 
        "fit": "Average", 
        "value": -0.07946207864132732
    }
}