{
    "Ar36": {
        "error": 0.0009572336242259433, 
        "filter_outliers_dict": {
            "filter_outliers": true, 
            "iterations": 1, 
            "std_devs": 2
        }, 
        "fit": "Parabolic", 
        "value": 0.2428080330347305
    }, 
    "Ar37": {
        "error": 0.0047358242443231655, 
        "filter_outliers_dict": {
            "filter_outliers": true, 
            "iterations": 1, 
            "std_devs": 2
        }, 
        "fit": "linear", 
        "value": 0.08376119937972945
    }, 
    "Ar38": {
        "error": 0.002304268674388061, 
        "filter_outliers_dict": {
            "filter_outliers": true, 
            "iterations": 1, 
            "std_devs": 2
        }, 
        "fit": "linear", 
        "value": 0.16976267139879525
    }, 
    "Ar39": {
        "error": 0.009838147284420404, 
        "filter_outliers_dict": {
            "filter_outliers": true, 
            "iterations": 1, 
            "std_devs": 2
        }, 
        "fit": "Parabolic", 
        "value": 10.521322622226023
    }, 
    "Ar40": {
        "error": 0.013651628559264588, 
        "filter_outliers_dict": {
            "filter_outliers": true, 
            "iterations": 1, 
            "std_devs": 2
        }, 
        "fit": "Parabolic", 
        "value": 81.90418239896198
    }, 
    "Ar41": {
        "error": 0.0036876013726364564, 
        "filter_outliers_dict": {
            "filter_outliers": true, 
            "iterations": 1, 
            "std_devs": 2
        }, 
        "fit": "linear", 
        "value": -0.06932028282123096
    }
}