{
    "Ar36": {
        "error": 0.0005421427281511532, 
        "filter_outliers_dict": {
            "filter_outliers": true, 
            "iterations": 1, 
            "std_devs": 2
        }, 
        "fit": "Parabolic", 
        "value": 0.0661885781028366
    }, 
    "Ar37": {
        "error": 0.00475823218407705, 
        "filter_outliers_dict": {
            "filter_outliers": true, 
            "iterations": 1, 
            "std_devs": 2
        }, 
        "fit": "linear", 
        "value": 0.05810803320650501
    }, 
    "Ar38": {
        "error": 0.002259539275586424, 
        "filter_outliers_dict": {
            "filter_outliers": true, 
            "iterations": 1, 
            "std_devs": 2
        }, 
        "fit": "linear", 
        "value": 0.04164242265659694
    }, 
    "Ar39": {
        "error": 0.009668199302362259, 
        "filter_outliers_dict": {
            "filter_outliers": true, 
            "iterations": 1, 
            "std_devs": 2
        }, 
        "fit": "Parabolic", 
        "value": 5.710103883783931
    }, 
    "Ar40": {
        "error": 0.010000269912469186, 
        "filter_outliers_dict": {
            "filter_outliers": true, 
            "iterations": 1, 
            "std_devs": 2
        }, 
        "fit": "Parabolic", 
        "value": 24.902468597338164
    }, 
    "Ar41": {
        "error": 0.011647523540140096, 
        "filter_outliers_dict": {
            "filter_outliers": true, 
            "iterations": 1, 
            "std_devs": 2
        }, 
        "fit": "linear", 
        "value": -0.17032135714324603
    }
}