{
    "Ar36": {
        "error": 0.0003046295493672232, 
        "filter_outliers_dict": {
            "filter_outliers": true, 
            "iterations": 1, 
            "std_devs": 10
        }, 
        "fit": "Parabolic", 
        "fn": 400, 
        "include_baseline_error": false, 
        "n": 400, 
        "value": 0.02011807729835155
    }, 
    "Ar37": {
        "error": 0.00453830382711168, 
        "filter_outliers_dict": {
            "filter_outliers": true, 
            "iterations": 1, 
            "std_devs": 2
        }, 
        "fit": "Linear", 
        "fn": 380, 
        "include_baseline_error": false, 
        "n": 400, 
        "value": 0.08801583769063528
    }, 
    "Ar38": {
        "error": 0.0020537738726765513, 
        "filter_outliers_dict": {
            "filter_outliers": true, 
            "iterations": 1, 
            "std_devs": 2
        }, 
        "fit": "Linear", 
        "fn": 381, 
        "include_baseline_error": false, 
        "n": 400, 
        "value": 0.1265749856297607
    }, 
    "Ar39": {
        "error": 0.009782583407059054, 
        "filter_outliers_dict": {
            "filter_outliers": true, 
            "iterations": 1, 
            "std_devs": 2
        }, 
        "fit": "Parabolic", 
        "fn": 381, 
        "include_baseline_error": false, 
        "n": 400, 
        "value": 10.884639925376216
    }, 
    "Ar40": {
        "error": 0.008886420637947656, 
        "filter_outliers_dict": {
            "filter_outliers": true, 
            "iterations": 1, 
            "std_devs": 2
        }, 
        "fit": "Parabolic", 
        "fn": 381, 
        "include_baseline_error": false, 
        "n": 400, 
        "value": 17.336656346984277
    }, 
    "Ar41": {
        "error": 0.0016302683178787852, 
        "filter_outliers_dict": {
            "filter_outliers": true, 
            "iterations": 1, 
            "std_devs": 2
        }, 
        "fit": "Average", 
        "fn": 385, 
        "include_baseline_error": false, 
        "n": 400, 
        "value": -0.08248412613696479
    }, 
    "reviewed": true
}