{
    "Ar36": {
        "error": 0.0008197932629529482, 
        "filter_outliers_dict": {
            "filter_outliers": true, 
            "iterations": 1, 
            "std_devs": 10
        }, 
        "fit": "Parabolic", 
        "fn": 120, 
        "include_baseline_error": false, 
        "n": 120, 
        "value": 0.01256887290700294
    }, 
    "Ar37": {
        "error": 0.010556173556271056, 
        "filter_outliers_dict": {
            "filter_outliers": true, 
            "iterations": 1, 
            "std_devs": 2
        }, 
        "fit": "Linear", 
        "fn": 115, 
        "include_baseline_error": false, 
        "n": 120, 
        "value": 0.04875019268508036
    }, 
    "Ar38": {
        "error": 0.004448427818894085, 
        "filter_outliers_dict": {
            "filter_outliers": true, 
            "iterations": 1, 
            "std_devs": 2
        }, 
        "fit": "Linear", 
        "fn": 115, 
        "include_baseline_error": false, 
        "n": 120, 
        "value": 0.01284802935094021
    }, 
    "Ar39": {
        "error": 0.019882342652027155, 
        "filter_outliers_dict": {
            "filter_outliers": true, 
            "iterations": 1, 
            "std_devs": 2
        }, 
        "fit": "Parabolic", 
        "fn": 114, 
        "include_baseline_error": false, 
        "n": 120, 
        "value": 1.9074900152128762
    }, 
    "Ar40": {
        "error": 0.02362182612936464, 
        "filter_outliers_dict": {
            "filter_outliers": true, 
            "iterations": 1, 
            "std_devs": 2
        }, 
        "fit": "Parabolic", 
        "fn": 114, 
        "include_baseline_error": false, 
        "n": 120, 
        "value": 24.98673337113385
    }, 
    "Ar41": {
        "error": 0.0038070687777513887, 
        "filter_outliers_dict": {
            "filter_outliers": true, 
            "iterations": 1, 
            "std_devs": 2
        }, 
        "fit": "Average", 
        "fn": 116, 
        "include_baseline_error": false, 
        "n": 120, 
        "value": -0.07292009738137431
    }, 
    "reviewed": true
}