{
    "Ar36": {
        "error": 0.00020503776206387076, 
        "filter_outliers_dict": {
            "filter_outliers": true, 
            "iterations": 1, 
            "std_devs": 2
        }, 
        "fit": "Linear", 
        "value": 0.00413690016837327
    }, 
    "Ar37": {
        "error": 0.008270875287198515, 
        "filter_outliers_dict": {
            "filter_outliers": true, 
            "iterations": 1, 
            "std_devs": 2
        }, 
        "fit": "linear", 
        "value": 0.03425958959536981
    }, 
    "Ar38": {
        "error": 0.0037426857388961335, 
        "filter_outliers_dict": {
            "filter_outliers": true, 
            "iterations": 1, 
            "std_devs": 2
        }, 
        "fit": "linear", 
        "value": 0.016662368551046365
    }, 
    "Ar39": {
        "error": 0.013138013004401407, 
        "filter_outliers_dict": {
            "filter_outliers": true, 
            "iterations": 1, 
            "std_devs": 2
        }, 
        "fit": "Linear", 
        "value": 2.813113626616594
    }, 
    "Ar40": {
        "error": 0.010067730203150532, 
        "filter_outliers_dict": {
            "filter_outliers": true, 
            "iterations": 1, 
            "std_devs": 2
        }, 
        "fit": "Linear", 
        "value": 2.2155232248582846
    }, 
    "Ar41": {
        "error": 0.010460114347542635, 
        "filter_outliers_dict": {
            "filter_outliers": true, 
            "iterations": 1, 
            "std_devs": 2
        }, 
        "fit": "Average", 
        "value": -0.1657690553109597
    }
}