{
    "Ar36": {
        "error": 0.0002098766226488804, 
        "filter_outliers_dict": {
            "filter_outliers": true, 
            "iterations": 1, 
            "std_devs": 2
        }, 
        "fit": "Parabolic", 
        "value": 0.008436896574884757
    }, 
    "Ar37": {
        "error": 0.005313173545962741, 
        "filter_outliers_dict": {
            "filter_outliers": true, 
            "iterations": 1, 
            "std_devs": 2
        }, 
        "fit": "linear", 
        "value": 0.08009021336232085
    }, 
    "Ar38": {
        "error": 0.0023357973006777346, 
        "filter_outliers_dict": {
            "filter_outliers": true, 
            "iterations": 1, 
            "std_devs": 2
        }, 
        "fit": "linear", 
        "value": 0.04542092536562929
    }, 
    "Ar39": {
        "error": 0.00921644391568899, 
        "filter_outliers_dict": {
            "filter_outliers": true, 
            "iterations": 1, 
            "std_devs": 2
        }, 
        "fit": "Parabolic", 
        "value": 5.025852137836279
    }, 
    "Ar40": {
        "error": 0.00899782764265257, 
        "filter_outliers_dict": {
            "filter_outliers": true, 
            "iterations": 1, 
            "std_devs": 2
        }, 
        "fit": "Parabolic", 
        "value": 5.784820877324468
    }, 
    "Ar41": {
        "error": 0.0039010161840069926, 
        "filter_outliers_dict": {
            "filter_outliers": true, 
            "iterations": 1, 
            "std_devs": 2
        }, 
        "fit": "linear", 
        "value": -0.06721083609432188
    }
}