{
    "Ar36": {
        "error": 0.0002717599679053571, 
        "filter_outliers_dict": {
            "filter_outliers": true, 
            "iterations": 1, 
            "std_devs": 2
        }, 
        "fit": "Linear", 
        "value": 0.011490395161012372
    }, 
    "Ar37": {
        "error": 0.010483404261112593, 
        "filter_outliers_dict": {
            "filter_outliers": true, 
            "iterations": 1, 
            "std_devs": 2
        }, 
        "fit": "linear", 
        "value": 0.08123434462651424
    }, 
    "Ar38": {
        "error": 0.005153337621058869, 
        "filter_outliers_dict": {
            "filter_outliers": true, 
            "iterations": 1, 
            "std_devs": 2
        }, 
        "fit": "linear", 
        "value": 0.04148368081451814
    }, 
    "Ar39": {
        "error": 0.010785940934724653, 
        "filter_outliers_dict": {
            "filter_outliers": true, 
            "iterations": 1, 
            "std_devs": 2
        }, 
        "fit": "Linear", 
        "value": 3.7270177120511407
    }, 
    "Ar40": {
        "error": 0.012538299747330067, 
        "filter_outliers_dict": {
            "filter_outliers": true, 
            "iterations": 1, 
            "std_devs": 2
        }, 
        "fit": "Linear", 
        "value": 15.798473286367528
    }, 
    "Ar41": {
        "error": 0.0034829995109921996, 
        "filter_outliers_dict": {
            "filter_outliers": true, 
            "iterations": 1, 
            "std_devs": 2
        }, 
        "fit": "Average", 
        "value": -0.07654841251232843
    }
}