{
    "Ar36": {
        "error": 0.00016362565261454957, 
        "filter_outliers_dict": {
            "filter_outliers": true, 
            "iterations": 1, 
            "std_devs": 2
        }, 
        "fit": "Parabolic", 
        "value": 0.00377598324655603
    }, 
    "Ar37": {
        "error": 0.004959584216434658, 
        "filter_outliers_dict": {
            "filter_outliers": true, 
            "iterations": 1, 
            "std_devs": 2
        }, 
        "fit": "linear", 
        "value": 0.0310131260323454
    }, 
    "Ar38": {
        "error": 0.0021741269166033555, 
        "filter_outliers_dict": {
            "filter_outliers": true, 
            "iterations": 1, 
            "std_devs": 2
        }, 
        "fit": "linear", 
        "value": -0.002722585980844153
    }, 
    "Ar39": {
        "error": 0.009243544478201922, 
        "filter_outliers_dict": {
            "filter_outliers": true, 
            "iterations": 1, 
            "std_devs": 2
        }, 
        "fit": "Parabolic", 
        "value": 1.8150488245304681
    }, 
    "Ar40": {
        "error": 0.007681748583415097, 
        "filter_outliers_dict": {
            "filter_outliers": true, 
            "iterations": 1, 
            "std_devs": 2
        }, 
        "fit": "Parabolic", 
        "value": 6.516892600518327
    }, 
    "Ar41": {
        "error": 0.011620298188808956, 
        "filter_outliers_dict": {
            "filter_outliers": true, 
            "iterations": 1, 
            "std_devs": 2
        }, 
        "fit": "linear", 
        "value": -0.13170808095927453
    }
}