{
    "Ar36": {
        "error": 0.00027188354155658847, 
        "filter_outliers_dict": {
            "filter_outliers": true, 
            "iterations": 1, 
            "std_devs": 2
        }, 
        "fit": "Parabolic", 
        "value": 0.014944064953391591
    }, 
    "Ar37": {
        "error": 0.005192794540040578, 
        "filter_outliers_dict": {
            "filter_outliers": true, 
            "iterations": 1, 
            "std_devs": 2
        }, 
        "fit": "linear", 
        "value": 0.10127977604070804
    }, 
    "Ar38": {
        "error": 0.00257931869885577, 
        "filter_outliers_dict": {
            "filter_outliers": true, 
            "iterations": 1, 
            "std_devs": 2
        }, 
        "fit": "linear", 
        "value": 0.11956600075552896
    }, 
    "Ar39": {
        "error": 0.010699062193893721, 
        "filter_outliers_dict": {
            "filter_outliers": true, 
            "iterations": 1, 
            "std_devs": 2
        }, 
        "fit": "Parabolic", 
        "value": 11.060877548208804
    }, 
    "Ar40": {
        "error": 0.009084224295484677, 
        "filter_outliers_dict": {
            "filter_outliers": true, 
            "iterations": 1, 
            "std_devs": 2
        }, 
        "fit": "Parabolic", 
        "value": 14.376783853236129
    }, 
    "Ar41": {
        "error": 0.003714160617538829, 
        "filter_outliers_dict": {
            "filter_outliers": true, 
            "iterations": 1, 
            "std_devs": 2
        }, 
        "fit": "linear", 
        "value": -0.08012909781975243
    }
}