{
    "Ar36": {
        "error": 0.0003888047337504057, 
        "filter_outliers_dict": {
            "filter_outliers": true, 
            "iterations": 1, 
            "std_devs": 2
        }, 
        "fit": "Parabolic", 
        "value": 0.044098190908555254
    }, 
    "Ar37": {
        "error": 0.00531735335117305, 
        "filter_outliers_dict": {
            "filter_outliers": true, 
            "iterations": 1, 
            "std_devs": 2
        }, 
        "fit": "linear", 
        "value": 0.14922552595641583
    }, 
    "Ar38": {
        "error": 0.0031434551100238614, 
        "filter_outliers_dict": {
            "filter_outliers": true, 
            "iterations": 1, 
            "std_devs": 2
        }, 
        "fit": "linear", 
        "value": 0.05910724401000131
    }, 
    "Ar39": {
        "error": 0.010056316509510176, 
        "filter_outliers_dict": {
            "filter_outliers": true, 
            "iterations": 1, 
            "std_devs": 2
        }, 
        "fit": "Parabolic", 
        "value": 15.832097379137588
    }, 
    "Ar40": {
        "error": 0.010273746202994274, 
        "filter_outliers_dict": {
            "filter_outliers": true, 
            "iterations": 1, 
            "std_devs": 2
        }, 
        "fit": "Parabolic", 
        "value": 33.93198923414431
    }, 
    "Ar41": {
        "error": 0.003595509019635827, 
        "filter_outliers_dict": {
            "filter_outliers": true, 
            "iterations": 1, 
            "std_devs": 2
        }, 
        "fit": "linear", 
        "value": -0.23905297467281958
    }
}