{
    "AX": {
        "error": 0.004608375049466614, 
        "filter_outliers_dict": {
            "filter_outliers": true, 
            "iterations": 1, 
            "std_devs": 2
        }, 
        "fit": "average", 
        "value": 0.14803300002154093
    }, 
    "CDD": {
        "error": 4.148307043564117e-06, 
        "filter_outliers_dict": {
            "filter_outliers": true, 
            "iterations": 1, 
            "std_devs": 10
        }, 
        "fit": "average", 
        "value": 1.2362092099416992e-05
    }, 
    "H1": {
        "error": 0.003783532693155664, 
        "filter_outliers_dict": {
            "filter_outliers": true, 
            "iterations": 1, 
            "std_devs": 2
        }, 
        "fit": "average", 
        "value": 0.08324875318327149
    }, 
    "H2": {
        "error": 0.002552584974828623, 
        "filter_outliers_dict": {
            "filter_outliers": true, 
            "iterations": 1, 
            "std_devs": 2
        }, 
        "fit": "average", 
        "value": -0.088171290181048
    }, 
    "L1": {
        "error": 0.0020341726959700527, 
        "filter_outliers_dict": {
            "filter_outliers": true, 
            "iterations": 1, 
            "std_devs": 2
        }, 
        "fit": "average", 
        "value": -0.015804214758860756
    }, 
    "L2": {
        "error": 0.003715438878269567, 
        "filter_outliers_dict": {
            "filter_outliers": true, 
            "iterations": 1, 
            "std_devs": 2
        }, 
        "fit": "average", 
        "value": -0.004974162558574521
    }
}