{
    "AX": {
        "error": 0.003960196454999822, 
        "filter_outliers_dict": {
            "filter_outliers": true, 
            "iterations": 1, 
            "std_devs": 2
        }, 
        "fit": "average", 
        "value": 0.13554866948882868
    }, 
    "CDD": {
        "error": 2.963783965864954e-06, 
        "filter_outliers_dict": {
            "filter_outliers": true, 
            "iterations": 1, 
            "std_devs": 10
        }, 
        "fit": "average", 
        "value": 7.4172552455029e-06
    }, 
    "H1": {
        "error": 0.0034539607801343263, 
        "filter_outliers_dict": {
            "filter_outliers": true, 
            "iterations": 1, 
            "std_devs": 2
        }, 
        "fit": "average", 
        "value": 0.07995292003851187
    }, 
    "H2": {
        "error": 0.0029169527444165154, 
        "filter_outliers_dict": {
            "filter_outliers": true, 
            "iterations": 1, 
            "std_devs": 2
        }, 
        "fit": "average", 
        "value": -0.0885424271187562
    }, 
    "L1": {
        "error": 0.0019358764401117379, 
        "filter_outliers_dict": {
            "filter_outliers": true, 
            "iterations": 1, 
            "std_devs": 2
        }, 
        "fit": "average", 
        "value": -0.022682412735786438
    }, 
    "L2": {
        "error": 0.003747885661943592, 
        "filter_outliers_dict": {
            "filter_outliers": true, 
            "iterations": 1, 
            "std_devs": 2
        }, 
        "fit": "average", 
        "value": -0.007891285637054593
    }
}