{
    "AX": {
        "error": 0.006538690586713554, 
        "filter_outliers_dict": {
            "filter_outliers": true, 
            "iterations": 1, 
            "std_devs": 2
        }, 
        "fit": "average", 
        "value": 0.15440698054236968
    }, 
    "CDD": {
        "error": 5.337800164872258e-06, 
        "filter_outliers_dict": {
            "filter_outliers": true, 
            "iterations": 1, 
            "std_devs": 10
        }, 
        "fit": "average", 
        "value": 1.2362092075838166e-05
    }, 
    "H1": {
        "error": 0.005110012263352139, 
        "filter_outliers_dict": {
            "filter_outliers": true, 
            "iterations": 1, 
            "std_devs": 2
        }, 
        "fit": "average", 
        "value": 0.08259241010996762
    }, 
    "H2": {
        "error": 0.003856624415852583, 
        "filter_outliers_dict": {
            "filter_outliers": true, 
            "iterations": 1, 
            "std_devs": 2
        }, 
        "fit": "average", 
        "value": -0.08603520664255478
    }, 
    "L1": {
        "error": 0.0028094743468940015, 
        "filter_outliers_dict": {
            "filter_outliers": true, 
            "iterations": 1, 
            "std_devs": 2
        }, 
        "fit": "average", 
        "value": -0.020433624390274373
    }, 
    "L2": {
        "error": 0.005610298889664918, 
        "filter_outliers_dict": {
            "filter_outliers": true, 
            "iterations": 1, 
            "std_devs": 2
        }, 
        "fit": "average", 
        "value": -0.013325289485964613
    }
}