{
    "AX": {
        "error": 0.004657291310806331, 
        "filter_outliers_dict": {
            "filter_outliers": true, 
            "iterations": 1, 
            "std_devs": 2
        }, 
        "fit": "average", 
        "value": 0.14441287225843172
    }, 
    "CDD": {
        "error": 2.963783965864954e-06, 
        "filter_outliers_dict": {
            "filter_outliers": true, 
            "iterations": 1, 
            "std_devs": 10
        }, 
        "fit": "average", 
        "value": 7.4172552455029e-06
    }, 
    "H1": {
        "error": 0.0036991005939627213, 
        "filter_outliers_dict": {
            "filter_outliers": true, 
            "iterations": 1, 
            "std_devs": 2
        }, 
        "fit": "average", 
        "value": 0.06361882978490277
    }, 
    "H2": {
        "error": 0.010230534586165588, 
        "filter_outliers_dict": {
            "filter_outliers": true, 
            "iterations": 1, 
            "std_devs": 2
        }, 
        "fit": "average", 
        "value": -0.1773214067841237
    }, 
    "L1": {
        "error": 0.0017393252371827005, 
        "filter_outliers_dict": {
            "filter_outliers": true, 
            "iterations": 1, 
            "std_devs": 2
        }, 
        "fit": "average", 
        "value": -0.028025687134595894
    }, 
    "L2": {
        "error": 0.0036956230847580017, 
        "filter_outliers_dict": {
            "filter_outliers": true, 
            "iterations": 1, 
            "std_devs": 2
        }, 
        "fit": "average", 
        "value": -0.021829531598495634
    }
}