{
    "AX": {
        "error": 0.004132342145827846, 
        "filter_outliers_dict": {
            "filter_outliers": true, 
            "iterations": 1, 
            "std_devs": 2
        }, 
        "fit": "average", 
        "value": 0.23663921453751863
    }, 
    "CDD": {
        "error": 4.901797760471196e-06, 
        "filter_outliers_dict": {
            "filter_outliers": true, 
            "iterations": 1, 
            "std_devs": 10
        }, 
        "fit": "average", 
        "value": 1.6070719745747265e-05
    }, 
    "H1": {
        "error": 0.0041725310425818965, 
        "filter_outliers_dict": {
            "filter_outliers": true, 
            "iterations": 1, 
            "std_devs": 2
        }, 
        "fit": "average", 
        "value": 0.10816124750192747
    }, 
    "H2": {
        "error": 0.0033380735759301087, 
        "filter_outliers_dict": {
            "filter_outliers": true, 
            "iterations": 1, 
            "std_devs": 2
        }, 
        "fit": "average", 
        "value": -0.25136132606336536
    }, 
    "L1": {
        "error": 0.0017290368235199068, 
        "filter_outliers_dict": {
            "filter_outliers": true, 
            "iterations": 1, 
            "std_devs": 2
        }, 
        "fit": "average", 
        "value": -0.15488550453269256
    }, 
    "L2": {
        "error": 0.004186011527368282, 
        "filter_outliers_dict": {
            "filter_outliers": true, 
            "iterations": 1, 
            "std_devs": 2
        }, 
        "fit": "average", 
        "value": 0.008548297653453767
    }
}